taibun/__init__.py
taibun/taibun.py
taibun/data/traditional.json
taibun/data/vars.json
taibun/data/words.json
example990420-1.1.2.dist-info/LICENSE
example990420-1.1.2.dist-info/METADATA
example990420-1.1.2.dist-info/WHEEL
example990420-1.1.2.dist-info/top_level.txt
example990420-1.1.2.dist-info/RECORD
