Metadata-Version: 2.1
Name: example990420
Version: 1.1.2
Summary: Taiwanese Hokkien Transliterator and Tokeniser
Home-page: https://github.com/andreihar/taibun
Author: Andrei Harbachov
Author-email: andrei.harbachov@gmail.com
License: MIT
Keywords: python,taiwan,taiwanese,taigi,hokkien,romanization,transliteration,transliterator,tokenization,tokenizer
Classifier: Topic :: Text Processing :: Linguistic
Classifier: Development Status :: 5 - Production/Stable
Classifier: Intended Audience :: Developers
Classifier: Programming Language :: Python :: 3
Classifier: Operating System :: Unix
Classifier: Operating System :: MacOS :: MacOS X
Classifier: Operating System :: Microsoft :: Windows
Requires-Python: >=3.8
License-File: LICENSE
